{
  "kind": "nobel_readiness_audit",
  "checkedAt": "2026-05-16T18:03:14.720Z",
  "passed": true,
  "targetRepo": null,
  "criteriaCount": 12,
  "domainCount": 10,
  "selectedDomainCount": 4,
  "candidateIdeaCount": 80,
  "rejectedCandidateCount": 68,
  "promotedCandidateCount": 12,
  "frozenPredictionCount": 24,
  "executedPredictionCount": 20,
  "holdoutExecutionCount": 12,
  "counterexampleExecutionCount": 16,
  "replayAttemptCount": 8,
  "killWeekAttackedCount": 40,
  "killWeekDowngradedCount": 12,
  "finalLabel": "promising_but_unvalidated",
  "forbiddenClaimFindings": [],
  "publicReviewUrlAuditStatus": null,
  "publicReviewUrlAuditPassed": null,
  "publicReviewUrlCount": null,
  "rawPublicReviewUrlCount": null,
  "artifactRefs": [
    ".sovryn/nobel-readiness/status.json",
    ".sovryn/nobel-readiness/criteria.json",
    ".sovryn/nobel-readiness/domain-selection.json",
    ".sovryn/nobel-readiness/candidate-search.json",
    ".sovryn/nobel-readiness/freeze-ledger.json",
    ".sovryn/nobel-readiness/execution-results.json",
    ".sovryn/nobel-readiness/holdout-results.json",
    ".sovryn/nobel-readiness/replay-results.json",
    ".sovryn/nobel-readiness/rival-theory-review.json",
    ".sovryn/nobel-readiness/readiness-score.json",
    ".sovryn/nobel-readiness/NOBEL_READINESS_REPORT.md"
  ],
  "evidenceHash": "05f23ef2afffc64f56e8d2c5fdfeafb483957336a38cf790e2dc84682fceedcf"
}
